proxyid/__init__.py
proxyid/__version__.py
proxyid/decorators.py
proxyid/encoding.py
proxyid/exceptions.py
proxyid/mixins.py
proxyid/utils/__init__.py
proxyid/utils/factory.py
proxyid/utils/helpers.py
proxyid-0.1.0.dist-info/LICENSE
proxyid-0.1.0.dist-info/METADATA
proxyid-0.1.0.dist-info/WHEEL
proxyid-0.1.0.dist-info/top_level.txt
proxyid-0.1.0.dist-info/RECORD
