Metadata-Version: 2.1
Name: proxyid
Version: 0.1.0
Summary: Proxyid hides your Django model primary key
Home-page: https://github.com/felipepaes/proxyid
Author: Felipe Paes
Author-email: felipepaes@disroot.org
License: FreeBSD License
Project-URL: Bug Tracker, https://github.com/felipepaes/proxyid/issues
Platform: UNKNOWN
Classifier: License :: OSI Approved :: BSD License
Classifier: Operating System :: OS Independent
Classifier: Programming Language :: Python :: 3.6
Classifier: Programming Language :: Python :: 3.7
Classifier: Programming Language :: Python :: 3.8
Classifier: Programming Language :: Python :: 3.9
Classifier: Framework :: Django :: 1.11
Classifier: Framework :: Django :: 2.0
Classifier: Framework :: Django :: 2.1
Classifier: Framework :: Django :: 2.2
Classifier: Framework :: Django :: 3.0
Classifier: Framework :: Django :: 3.1
Requires-Python: >=3.6
Requires-Dist: hashids
